[
  {
    "id" : "glpi",
    "name" : "Mise en place de GLPI",
    "logo" : "glpi.png",
    "img" : "glpi.png",
    "link" : ""
  },

  {
    "id" : "groupe_AD",
    "name" : "Procédure - Gestion des stratégies de groupe",
    "logo" : "groupe.png",
    "img" : "groupe.png",
    "link" : "ressources/Strategie_de_groupe.pdf"
  },
    
  {
    "id" : "gitlab",
    "name" : "Procédure - Mise en place de GitLab",
    "logo" : "gitLab.png",
    "img" : "gitLab.png",
    "link" : "ressources/Procédure_-_Mise_en_place_de_GitLab.pdf"
  }, 
  
  {
    "id" : "linkedin",
    "name" : "Compte Linkedin",
    "logo" : "linkdin.png",
    "img" : "linkdin.png",
    "link" : "https://fr.linkedin.com/in/kevin-fort-45e"
  }, 

  {
    "id" : "github",
    "name" : "Compte GitHub et importation de mes projets",
    "logo" : "github.png",
    "img" : "github.png",
    "link" : "https://github.com/ShikiFutakiPP"
  },

  {
    "id" : "portfolio",
    "name" : "Portfolio",
    "logo" : "portfolio.png",
    "img" : "portfolio.png",
    "link" : "https://github.com/ShikiFutakiPP/portfolio"
  },

  {
    "id" : "devops",
    "name" : "Formation Devops",
    "logo" : "azure.png",
    "img" : "azure.png",
    "link" : "ressources/azure.png"
  },
       
  {
    "id" : "bucket",
    "name" : "Site de gestion de liste de choses à faire<br/>(Bucket List)",
    "logo" : "bucket-list.png",
    "img" : "bucket-list.png",
    "link" : "https://github.com/ShikiFutakiPP/bucket-list"
  },

  {
    "id" : "msl",
    "name" : "Site d'auto-évaluation par compétence et leur suivi<br/>(MSL)",
    "logo" : "MSL.png",
    "img" : "MSL.png",
    "link" : "https://github.com/ShikiFutakiPP/MSL.git"
  },  

  {
    "id" : "stage",
    "name" : "Site de suivi des demandes et documents pour les stages",
    "logo" : "stage.png",
    "img" : "stage.png",
    "link" : "https://github.com/armanceau2/Stages2023"
  },

  {
    "id" : "lafleur",
    "name" : "Site de commandes de fleurs et de gestion des stocks<br/>(Lafleur)",
    "logo" : "lafleur.png",
    "img" : "lafleur.png",
    "link" : "https://github.com/DylanAndradePereira/Lafleur"
  },

  {
    "id" : "mairie",
    "name" : "Site de partage des documents et gestion des rapports pour les Astreintes<br/>(Mairie Fleury)",
    "logo" : "mairie.png",
    "img" : "mairie.png",
    "link" : "https://github.com/ShikiFutakiPP/astreinte"
  }
]